setup.py
django_templatehooks.egg-info/PKG-INFO
django_templatehooks.egg-info/SOURCES.txt
django_templatehooks.egg-info/dependency_links.txt
django_templatehooks.egg-info/not-zip-safe
django_templatehooks.egg-info/top_level.txt
templatehooks/__init__.py
templatehooks/decorators.py
templatehooks/models.py
templatehooks/registry.py
templatehooks/templatetags/__init__.py
templatehooks/templatetags/templatehooks.py